gsmvi/__init__.py
gsmvi/advi.py
gsmvi/gsm.py
gsmvi/gsm_numpy.py
gsmvi/initializers.py
gsmvi/monitors.py
gsmvi-0.1.dist-info/LICENSE
gsmvi-0.1.dist-info/METADATA
gsmvi-0.1.dist-info/WHEEL
gsmvi-0.1.dist-info/top_level.txt
gsmvi-0.1.dist-info/RECORD
