Metadata-Version: 2.1
Name: gsmvi
Version: 0.1
Summary: Implementation of Gaussian score matching for variational inference (arXiv:2307.07849)
Author-email: Chirag Modi <modichirag92@gmail.com>
Project-URL: Homepage, https://github.com/modichirag/GSM-VI/
Classifier: Programming Language :: Python :: 3
Classifier: License :: OSI Approved :: MIT License
Classifier: Operating System :: OS Independent
Requires-Python: >=3.8
License-File: LICENSE
Provides-Extra: full
Requires-Dist: jax ; extra == 'full'
Requires-Dist: jaxlib ; extra == 'full'
Requires-Dist: numpyro ; extra == 'full'
Requires-Dist: optax ; extra == 'full'
Requires-Dist: scipy ; extra == 'full'
